LICENSE
README.md
setup.py
bin/__init__.py
bin/codecomrade
codecomrade/__init__.py
codecomrade/main.py
codecomrade.egg-info/PKG-INFO
codecomrade.egg-info/SOURCES.txt
codecomrade.egg-info/dependency_links.txt
codecomrade.egg-info/requires.txt
codecomrade.egg-info/top_level.txt